<campusRoot>
  <Header 
  accountabilityEnabled="false" batchThreads="0" batchQueueEnabled="false" simsLinked="false" ldapAuthenticationEnabled="false" stateLinked="KYStateCampus" taskScheduler="false" financeEnabled="false" hrEnabled="false" posEnable="false" logoutDelay="5" refreshLimit="11" refreshMinutes="5" appletGZip="true" clientIP="/10.232.1.175" isSafari="true" isGecko="false" isMac="false" isIE="false" onlinePaymentsMode="TEST" dataMartsEnabled="false" onlinePaymentsEnabled="null" quartzSchedulerEnabled="false" campusIDEEnabled="false" shoutpointEnabled="false" messengerEnabled="true" userAgent="Mozilla/5.0 (X11; Linux x86_64) AppleWebKit/535.1 (KHTML, like Gecko) Chrome/13.0.782.112 Safari/535.1" districtNumber="275" edition="district" group="" state="KY" appServer="app7" appName="jcps" yearScope="2012" sectionScope="685008" structureScope="3976" districtScope="86" schoolScope="119" calendarScope="2963" calendarCookie="2963" time="06:04:08 PM" date="08/21/2011" baseURL="https://infinitecampus.jefferson.kyschools.us/public/">
    <Param value="extract.xml" name="saveAs"></Param>
    <Param value="2963" name="calendarID"></Param>
    <Param value="17418" name="filterID"></Param>
    <Param value="adhoc.AdHocFilter-listAdhocData" name="x"></Param>
    <Param value="live" name="source"></Param>
    <User 
    calendarCount="4" OLPAccountID="0" sessionID="0" districtID="86" firstName="Todd" lastName="O'Bryan" personID="736052" hideToolbar="false" hideBanner="false" allCalendars="0" allModules="0" username="tobryan1" userID="8930">
</User>
</Header>
  <ExportWizard>
    <DisplayPreferences>
      <Field nooutput="false" type="varchar" attribute="individual.lastName" name="lastName"></Field>
      <Field nooutput="false" type="varchar" attribute="individual.firstName" name="firstName"></Field>
      <Field nooutput="false" type="varchar" attribute="individual.middleName" name="middleName"></Field>
      <Field nooutput="false" type="varchar" attribute="individual.suffix" name="suffix"></Field>
      <Field nooutput="false" type="char" attribute="individual.gender" name="gender"></Field>
      <Field nooutput="false" type="int" attribute="individual.personID" name="personID"></Field>
      <Field nooutput="false" type="varchar" attribute="individual.staffNumber" name="staffNumber"></Field>
      <Field nooutput="false" type="varchar" attribute="schoolEmployment.schoolNumber" name="schoolNumber"></Field>
      <Field nooutput="false" type="varchar" attribute="individual.stateID" name="stateID"></Field>
      <Field nooutput="false" type="varchar" attribute="pcontact.email" name="email"></Field>
      <Field nooutput="false" type="varchar" attribute="individual.alias" name="alias"></Field>
    </DisplayPreferences>
    <Extract name="accuscholar-teachers">
      <group dataColumns="11" value="Records" groupSort="ASC" groupBy="All" tier="0">
        <person 
        individual.alias="Jabell1" pcontact.email="Joshua.Abell@jefferson.kyschools.us" individual.stateID="1950108587" schoolEmployment.schoolNumber="200" individual.staffNumber="128061" individual.personID="4574" individual.gender="M" individual.suffix="" individual.middleName="L" individual.firstName="Joshua" individual.lastName="Abell">
</person>
        <person 
        individual.alias="Babney1" pcontact.email="betty.abney@jefferson.kyschools.us" individual.stateID="" schoolEmployment.schoolNumber="200" individual.staffNumber="130437" individual.personID="889696" individual.gender="F" individual.suffix="" individual.middleName="" individual.firstName="Betty" individual.lastName="Abney">
</person>
        <person 
        individual.alias="" pcontact.email="John.Albright@Jefferson.kyschools.us" individual.stateID="211007137" schoolEmployment.schoolNumber="200" individual.staffNumber="111309" individual.personID="738692" individual.gender="M" individual.suffix="" individual.middleName="" individual.firstName="John" individual.lastName="Albright">
</person>
        <person 
        individual.alias="" pcontact.email="Alana.Alford@Jefferson.kyschools.us" individual.stateID="211009758" schoolEmployment.schoolNumber="200" individual.staffNumber="116976" individual.personID="741721" individual.gender="F" individual.suffix="" individual.middleName="F" individual.firstName="Alana" individual.lastName="Alford">
</person>
        <person 
        individual.alias="" pcontact.email="Eric.Allgeier@jefferson.kyschools.us" individual.stateID="211003439" schoolEmployment.schoolNumber="200" individual.staffNumber="122757" individual.personID="743731" individual.gender="M" individual.suffix="" individual.middleName="" individual.firstName="Eric" individual.lastName="Allgeier">
</person>
        <person 
        individual.alias="" pcontact.email="Pat.Allison@Jefferson.kyschools.us" individual.stateID="211006714" schoolEmployment.schoolNumber="200" individual.staffNumber="118701" individual.personID="742660" individual.gender="F" individual.suffix="" individual.middleName="Dodson" individual.firstName="Patricia" individual.lastName="Allison">
</person>
        <person 
        individual.alias="" pcontact.email="anthony.allsmiller@jefferson.kyschools.us" individual.stateID="" schoolEmployment.schoolNumber="200" individual.staffNumber="130865" individual.personID="904397" individual.gender="M" individual.suffix="" individual.middleName="Scott" individual.firstName="Anthony" individual.lastName="Allsmiller">
</person>
        <person 
        individual.alias="" pcontact.email="Patty.Armstrong@Jefferson.kyschools.us" individual.stateID="211001313" schoolEmployment.schoolNumber="200" individual.staffNumber="102674" individual.personID="734074" individual.gender="F" individual.suffix="" individual.middleName="" individual.firstName="Patty" individual.lastName="Armstrong">
</person>
        <person 
        individual.alias="" pcontact.email="Holly.Atsvsdi@Jefferson.kyschools.us" individual.stateID="211007961" schoolEmployment.schoolNumber="200" individual.staffNumber="104503" individual.personID="735063" individual.gender="F" individual.suffix="" individual.middleName="" individual.firstName="Usdasd" individual.lastName="Atsvsdi">
</person>
        <person 
        individual.alias="" pcontact.email="robertl.baar@jefferson.kyschools.us" individual.stateID="" schoolEmployment.schoolNumber="200" individual.staffNumber="100524" individual.personID="732906" individual.gender="M" individual.suffix="" individual.middleName="" individual.firstName="Bob" individual.lastName="Baar">
</person>
        <person 
        individual.alias="" pcontact.email="Beverly.Bailey@Jefferson.kyschools.us" individual.stateID="211011514" schoolEmployment.schoolNumber="200" individual.staffNumber="113702" individual.personID="739968" individual.gender="F" individual.suffix="" individual.middleName="" individual.firstName="Beverly" individual.lastName="Bailey">
</person>
        <person 
        individual.alias="wbass1" pcontact.email="William.Bass@jefferson.kyschools.us" individual.stateID="" schoolEmployment.schoolNumber="200" individual.staffNumber="129906" individual.personID="867560" individual.gender="M" individual.suffix="" individual.middleName="" individual.firstName="William" individual.lastName="Bass">
</person>
        <person 
        individual.alias="" pcontact.email="Betsey.Bell@Jefferson.kyschools.us" individual.stateID="211017009" schoolEmployment.schoolNumber="200" individual.staffNumber="106847" individual.personID="736285" individual.gender="F" individual.suffix="" individual.middleName="" individual.firstName="Betsey" individual.lastName="Bell">
</person>
        <person 
        individual.alias="" pcontact.email="Doris.Bell-Murphy@Jefferson.kyschools.us" individual.stateID="211003831" schoolEmployment.schoolNumber="200" individual.staffNumber="101911" individual.personID="733664" individual.gender="F" individual.suffix="" individual.middleName="" individual.firstName="Doris" individual.lastName="Bell-Murphy">
</person>
        <person 
        individual.alias="" pcontact.email="Gail.Benedict@Jefferson.kyschools.us" individual.stateID="211006361" schoolEmployment.schoolNumber="200" individual.staffNumber="107703" individual.personID="736767" individual.gender="F" individual.suffix="" individual.middleName="" individual.firstName="Gail" individual.lastName="Benedict">
</person>
        <person 
        individual.alias="" pcontact.email="andrew.benner@jefferson.kyschools.us" individual.stateID="211009438" schoolEmployment.schoolNumber="200" individual.staffNumber="114413" individual.personID="740342" individual.gender="M" individual.suffix="" individual.middleName="D" individual.firstName="Andrew" individual.lastName="Benner">
</person>
        <person 
        individual.alias="" pcontact.email="Erin.Black@jefferson.kyschools.us" individual.stateID="1950339315" schoolEmployment.schoolNumber="200" individual.staffNumber="128486" individual.personID="22217" individual.gender="F" individual.suffix="" individual.middleName="D" individual.firstName="Erin" individual.lastName="Black">
</person>
        <person 
        individual.alias="" pcontact.email="Shelly.Boles@Jefferson.kyschools.us" individual.stateID="211005389" schoolEmployment.schoolNumber="200" individual.staffNumber="103561" individual.personID="734549" individual.gender="F" individual.suffix="" individual.middleName="R" individual.firstName="Shelly" individual.lastName="Boles">
</person>
        <person 
        individual.alias="" pcontact.email="linda.boutiette@jefferson.kyschools.us" individual.stateID="2120284143" schoolEmployment.schoolNumber="200" individual.staffNumber="113651" individual.personID="826344" individual.gender="F" individual.suffix="" individual.middleName="J" individual.firstName="Linda" individual.lastName="Boutiette">
</person>
        <person 
        individual.alias="" pcontact.email="William.Bradford@jefferson.kyschools.us" individual.stateID="211010159" schoolEmployment.schoolNumber="200" individual.staffNumber="116689" individual.personID="741568" individual.gender="M" individual.suffix="" individual.middleName="Pryor" individual.firstName="William" individual.lastName="Bradford">
</person>
        <person 
        individual.alias="" pcontact.email="melissa.brant@jefferson.kyschools.us" individual.stateID="" schoolEmployment.schoolNumber="200" individual.staffNumber="131060" individual.personID="310473" individual.gender="F" individual.suffix="" individual.middleName="Gail" individual.firstName="Melissa" individual.lastName="Brant">
</person>
        <person 
        individual.alias="" pcontact.email="Thayne.Trotter@jefferson.kyschools.us" individual.stateID="211009240" schoolEmployment.schoolNumber="200" individual.staffNumber="122810" individual.personID="743772" individual.gender="F" individual.suffix="" individual.middleName="" individual.firstName="Thayne" individual.lastName="Bruszewski">
</person>
        <person 
        individual.alias="" pcontact.email="Elizabeth.Bunting@Jefferson.kyschools.us" individual.stateID="211009232" schoolEmployment.schoolNumber="200" individual.staffNumber="100220" individual.personID="732744" individual.gender="F" individual.suffix="" individual.middleName="" individual.firstName="Elizabeth" individual.lastName="Bunting">
</person>
        <person 
        individual.alias="" pcontact.email="Janice.Burden@Jefferson.kyschools.us" individual.stateID="211001283" schoolEmployment.schoolNumber="200" individual.staffNumber="121440" individual.personID="743392" individual.gender="F" individual.suffix="" individual.middleName="" individual.firstName="Janice" individual.lastName="Burden">
</person>
        <person 
        individual.alias="kburnet1" pcontact.email="Kathleen.Burnett@Jefferson.kyschools.us" individual.stateID="211005925" schoolEmployment.schoolNumber="200" individual.staffNumber="106703" individual.personID="736219" individual.gender="F" individual.suffix="" individual.middleName="Mary" individual.firstName="Kathleen" individual.lastName="Burnett">
</person>
        <person 
        individual.alias="" pcontact.email="edward.burton@jefferson.kyschools.us" individual.stateID="" schoolEmployment.schoolNumber="200" individual.staffNumber="125355" individual.personID="904400" individual.gender="M" individual.suffix="" individual.middleName="" individual.firstName="Edward" individual.lastName="Burton">
</person>
        <person 
        individual.alias="" pcontact.email="n@n.com" individual.stateID="" schoolEmployment.schoolNumber="200" individual.staffNumber="999999" individual.personID="732448" individual.gender="M" individual.suffix="" individual.middleName="" individual.firstName="Null" individual.lastName="Bus Driver">
</person>
        <person 
        individual.alias="" pcontact.email="Robin.Cash@Jefferson.kyschools.us" individual.stateID="211002541" schoolEmployment.schoolNumber="200" individual.staffNumber="111666" individual.personID="738868" individual.gender="F" individual.suffix="" individual.middleName="" individual.firstName="Robin" individual.lastName="Cash">
</person>
        <person 
        individual.alias="" pcontact.email="Ana.Castro@Jefferson.kyschools.us" individual.stateID="211005346" schoolEmployment.schoolNumber="200" individual.staffNumber="115199" individual.personID="740758" individual.gender="F" individual.suffix="" individual.middleName="" individual.firstName="Ana" individual.lastName="Castro">
</person>
        <person 
        individual.alias="" pcontact.email="Christina.Causey@jefferson.kyschools.us" individual.stateID="2120284009" schoolEmployment.schoolNumber="200" individual.staffNumber="124129" individual.personID="821747" individual.gender="F" individual.suffix="" individual.middleName="C" individual.firstName="Christina" individual.lastName="Causey">
</person>
        <person 
        individual.alias="" pcontact.email="mwchaddic@aol.com" individual.stateID="" schoolEmployment.schoolNumber="200" individual.staffNumber="132299" individual.personID="687685" individual.gender="M" individual.suffix="" individual.middleName="W" individual.firstName="Mark" individual.lastName="Chaddic">
</person>
        <person 
        individual.alias="" pcontact.email="Carol.Cheever@Jefferson.kyschools.us" individual.stateID="211013167" schoolEmployment.schoolNumber="200" individual.staffNumber="107232" individual.personID="736512" individual.gender="F" individual.suffix="" individual.middleName="" individual.firstName="Caro" individual.lastName="Cheever">
</person>
        <person 
        individual.alias="" pcontact.email="Robin.Ford@Jefferson.kyschools.us" individual.stateID="211008326" schoolEmployment.schoolNumber="200" individual.staffNumber="107455" individual.personID="736634" individual.gender="F" individual.suffix="" individual.middleName="" individual.firstName="Robin" individual.lastName="Clanton">
</person>
        <person 
        individual.alias="" pcontact.email="tammy.clements@jefferson.kyschools.us" individual.stateID="2120171410" schoolEmployment.schoolNumber="200" individual.staffNumber="103029" individual.personID="758608" individual.gender="F" individual.suffix="" individual.middleName="C" individual.firstName="Tammy" individual.lastName="Clements">
</person>
        <person 
        individual.alias="" pcontact.email="Beverly.Coffey@jefferson.kyschools.us" individual.stateID="2120252698" schoolEmployment.schoolNumber="200" individual.staffNumber="127054" individual.personID="771538" individual.gender="F" individual.suffix="" individual.middleName="" individual.firstName="Beverly" individual.lastName="Coffey">
</person>
        <person 
        individual.alias="" pcontact.email="Carolyn.Collesano@Jefferson.kyschools.us" individual.stateID="211008450" schoolEmployment.schoolNumber="200" individual.staffNumber="111667" individual.personID="738869" individual.gender="F" individual.suffix="" individual.middleName="" individual.firstName="Carolyn" individual.lastName="Collesano">
</person>
        <person 
        individual.alias="scommon1" pcontact.email="Sandra.Commons@Jefferson.kyschools.us" individual.stateID="211006386" schoolEmployment.schoolNumber="200" individual.staffNumber="112282" individual.personID="739202" individual.gender="F" individual.suffix="" individual.middleName="J" individual.firstName="Sandra" individual.lastName="Commons">
</person>
        <person 
        individual.alias="scorri1" pcontact.email="shannon.corrigan@jefferson.kyschools.us" individual.stateID="" schoolEmployment.schoolNumber="200" individual.staffNumber="133039" individual.personID="926316" individual.gender="F" individual.suffix="" individual.middleName="Leigh" individual.firstName="Shannon" individual.lastName="Corrigan">
</person>
        <person 
        individual.alias="" pcontact.email="Lamont.Cowden@Jefferson.kyschools.us" individual.stateID="211014320" schoolEmployment.schoolNumber="200" individual.staffNumber="105303" individual.personID="735484" individual.gender="M" individual.suffix="" individual.middleName="Lamont" individual.firstName="Fred" individual.lastName="Cowden">
</person>
        <person 
        individual.alias="" pcontact.email="Bryan.Crady@Jefferson.kyschools.us" individual.stateID="211005720" schoolEmployment.schoolNumber="200" individual.staffNumber="108828" individual.personID="737352" individual.gender="M" individual.suffix="" individual.middleName="L" individual.firstName="Bryan" individual.lastName="Crady">
</person>
        <person 
        individual.alias="" pcontact.email="Jane.Crady@Jefferson.kyschools.us" individual.stateID="211013895" schoolEmployment.schoolNumber="200" individual.staffNumber="114521" individual.personID="740396" individual.gender="F" individual.suffix="" individual.middleName="I" individual.firstName="Jane" individual.lastName="Crady">
</person>
        <person 
        individual.alias="" pcontact.email="Michael.Crain@Jefferson.kyschools.us" individual.stateID="211013989" schoolEmployment.schoolNumber="200" individual.staffNumber="112345" individual.personID="739241" individual.gender="M" individual.suffix="" individual.middleName="" individual.firstName="Joseph" individual.lastName="Crain">
</person>
        <person 
        individual.alias="" pcontact.email="David.Crawford@Jefferson.kyschools.us" individual.stateID="211010061" schoolEmployment.schoolNumber="200" individual.staffNumber="105375" individual.personID="735514" individual.gender="M" individual.suffix="" individual.middleName="" individual.firstName="David" individual.lastName="Crawford">
</person>
        <person 
        individual.alias="" pcontact.email="Lester.Crayton@jefferson.kyschools.us" individual.stateID="211016159" schoolEmployment.schoolNumber="200" individual.staffNumber="115610" individual.personID="740976" individual.gender="M" individual.suffix="" individual.middleName="" individual.firstName="Lester" individual.lastName="Crayton">
</person>
        <person 
        individual.alias="" pcontact.email="yoofi.crentsil@jefferson.kyschools.us" individual.stateID="211017018" schoolEmployment.schoolNumber="200" individual.staffNumber="115006" individual.personID="740660" individual.gender="M" individual.suffix="" individual.middleName="" individual.firstName="Yoofi" individual.lastName="Crentsil">
</person>
        <person 
        individual.alias="dcruze1" pcontact.email="debbie.cruze@jefferson.kyschools.us" individual.stateID="211012436" schoolEmployment.schoolNumber="200" individual.staffNumber="117751" individual.personID="742171" individual.gender="F" individual.suffix="" individual.middleName="" individual.firstName="Deborah" individual.lastName="Cruze">
</person>
        <person 
        individual.alias="" pcontact.email="Wes.Curtis@Jefferson.kyschools.us" individual.stateID="211001134" schoolEmployment.schoolNumber="200" individual.staffNumber="118182" individual.personID="742386" individual.gender="M" individual.suffix="" individual.middleName="" individual.firstName="Wesley" individual.lastName="Curtis">
</person>
        <person 
        individual.alias="" pcontact.email="David.Dallmann@Jefferson.kyschools.us" individual.stateID="211008926" schoolEmployment.schoolNumber="200" individual.staffNumber="106564" individual.personID="736154" individual.gender="M" individual.suffix="" individual.middleName="" individual.firstName="David" individual.lastName="Dallmann">
</person>
        <person 
        individual.alias="" pcontact.email="Craig.Darif@Jefferson.kyschools.us" individual.stateID="211017480" schoolEmployment.schoolNumber="200" individual.staffNumber="114928" individual.personID="740614" individual.gender="M" individual.suffix="" individual.middleName="" individual.firstName="Craig" individual.lastName="Darif">
</person>
        <person 
        individual.alias="" pcontact.email="william.darling@jefferson.kyschools.us" individual.stateID="211004223" schoolEmployment.schoolNumber="200" individual.staffNumber="121590" individual.personID="743414" individual.gender="M" individual.suffix="" individual.middleName="L" individual.firstName="William" individual.lastName="Darling">
</person>
        <person 
        individual.alias="" pcontact.email="Erica.Darnell@jefferson.kyschools.us" individual.stateID="211007814" schoolEmployment.schoolNumber="200" individual.staffNumber="122896" individual.personID="743837" individual.gender="F" individual.suffix="" individual.middleName="L" individual.firstName="Erica" individual.lastName="Darnell">
</person>
        <person 
        individual.alias="" pcontact.email="Jeffrey.Davis@Jefferson.kyschools.us" individual.stateID="211004660" schoolEmployment.schoolNumber="200" individual.staffNumber="117528" individual.personID="742037" individual.gender="M" individual.suffix="" individual.middleName="" individual.firstName="Jeffrey" individual.lastName="Davis">
</person>
        <person 
        individual.alias="" pcontact.email="rachel.davis2@jefferson.kyschools.us" individual.stateID="211011287" schoolEmployment.schoolNumber="200" individual.staffNumber="101642" individual.personID="733513" individual.gender="F" individual.suffix="" individual.middleName="H" individual.firstName="Rachel" individual.lastName="Davis">
</person>
        <person 
        individual.alias="" pcontact.email="Susan.Davis1@Jefferson.kyschools.us" individual.stateID="211007295" schoolEmployment.schoolNumber="200" individual.staffNumber="102320" individual.personID="733883" individual.gender="F" individual.suffix="" individual.middleName="" individual.firstName="Susan" individual.lastName="Davis">
</person>
        <person 
        individual.alias="" pcontact.email="kelli.dehr@jefferson.kyschools.us" individual.stateID="1950821171" schoolEmployment.schoolNumber="200" individual.staffNumber="126049" individual.personID="53424" individual.gender="F" individual.suffix="" individual.middleName="Marie" individual.firstName="Kelli" individual.lastName="Dehr">
</person>
        <person 
        individual.alias="" pcontact.email="Bill.Deines@Jefferson.kyschools.us" individual.stateID="211012759" schoolEmployment.schoolNumber="200" individual.staffNumber="107366" individual.personID="736591" individual.gender="M" individual.suffix="" individual.middleName="" individual.firstName="William" individual.lastName="Deines">
</person>
        <person 
        individual.alias="" pcontact.email="Douglas.DeWeese@Jefferson.kyschools.us" individual.stateID="211015110" schoolEmployment.schoolNumber="200" individual.staffNumber="115807" individual.personID="741085" individual.gender="M" individual.suffix="" individual.middleName="" individual.firstName="Douglas" individual.lastName="Deweese">
</person>
        <person 
        individual.alias="" pcontact.email="Rebecca.Donahoe@Jefferson.kyschools.us" individual.stateID="211001504" schoolEmployment.schoolNumber="200" individual.staffNumber="107601" individual.personID="736713" individual.gender="F" individual.suffix="" individual.middleName="" individual.firstName="Rebecca" individual.lastName="Donahoe">
</person>
        <person 
        individual.alias="ldonahu1" pcontact.email="laura.donahue@jefferson.kyschools.us" individual.stateID="" schoolEmployment.schoolNumber="200" individual.staffNumber="103912" individual.personID="734747" individual.gender="F" individual.suffix="" individual.middleName="F" individual.firstName="Laura" individual.lastName="Donahue">
</person>
        <person 
        individual.alias="" pcontact.email="nancy.duerr@jefferson.kyschools.us" individual.stateID="" schoolEmployment.schoolNumber="200" individual.staffNumber="131950" individual.personID="915134" individual.gender="F" individual.suffix="" individual.middleName="K" individual.firstName="Nancy" individual.lastName="Duerr">
</person>
        <person 
        individual.alias="" pcontact.email="Frances.Duffy@Jefferson.kyschools.us" individual.stateID="211013168" schoolEmployment.schoolNumber="200" individual.staffNumber="106301" individual.personID="736022" individual.gender="F" individual.suffix="" individual.middleName="" individual.firstName="Frances" individual.lastName="Duffy">
</person>
        <person 
        individual.alias="" pcontact.email="Ben.Easley@Jefferson.kyschools.us" individual.stateID="" schoolEmployment.schoolNumber="200" individual.staffNumber="105274" individual.personID="735472" individual.gender="M" individual.suffix="" individual.middleName="J." individual.firstName="Benjamin" individual.lastName="Easley">
</person>
        <person 
        individual.alias="keastr1" pcontact.email="Kevin.Eastridge@jefferson.kyschools.us" individual.stateID="" schoolEmployment.schoolNumber="200" individual.staffNumber="129779" individual.personID="862376" individual.gender="M" individual.suffix="" individual.middleName="Todd" individual.firstName="Kevin" individual.lastName="Eastridge">
</person>
        <person 
        individual.alias="" pcontact.email="Rayna.Eberhardt@Jefferson.kyschools.us" individual.stateID="" schoolEmployment.schoolNumber="200" individual.staffNumber="111296" individual.personID="738682" individual.gender="F" individual.suffix="" individual.middleName="R." individual.firstName="Rayna" individual.lastName="Eberhardt">
</person>
        <person 
        individual.alias="" pcontact.email="Lanette.Edwards@jefferson.kyschools.us" individual.stateID="211005364" schoolEmployment.schoolNumber="200" individual.staffNumber="124944" individual.personID="299166" individual.gender="F" individual.suffix="" individual.middleName="R" individual.firstName="Lanette" individual.lastName="Edwards">
</person>
        <person 
        individual.alias="" pcontact.email="Curtis.Essig@Jefferson.kyschools.us" individual.stateID="211011646" schoolEmployment.schoolNumber="200" individual.staffNumber="106897" individual.personID="736314" individual.gender="M" individual.suffix="" individual.middleName="" individual.firstName="Curtis" individual.lastName="Essig">
</person>
        <person 
        individual.alias="" pcontact.email="Francoise.Farman@Jefferson.kyschools.us" individual.stateID="211010936" schoolEmployment.schoolNumber="200" individual.staffNumber="111536" individual.personID="738800" individual.gender="F" individual.suffix="" individual.middleName="" individual.firstName="Francoise" individual.lastName="Farman">
</person>
        <person 
        individual.alias="" pcontact.email="Darryl.Farmer@jefferson.kyschools.us" individual.stateID="" schoolEmployment.schoolNumber="200" individual.staffNumber="128815" individual.personID="844682" individual.gender="M" individual.suffix="" individual.middleName="W" individual.firstName="Darryl" individual.lastName="Farmer">
</person>
        <person 
        individual.alias="" pcontact.email="jeremy.fey@jefferson.kyschools.us" individual.stateID="" schoolEmployment.schoolNumber="200" individual.staffNumber="129529" individual.personID="905013" individual.gender="M" individual.suffix="" individual.middleName="E" individual.firstName="Jeremy" individual.lastName="Fey">
</person>
        <person 
        individual.alias="" pcontact.email="Nicole.Finley@Jefferson.kyschools.us" individual.stateID="211013490" schoolEmployment.schoolNumber="200" individual.staffNumber="118001" individual.personID="570404" individual.gender="F" individual.suffix="" individual.middleName="B" individual.firstName="Nicole" individual.lastName="Finley">
</person>
        <person 
        individual.alias="" pcontact.email="Dyanne.Fowler@Jefferson.kyschools.us" individual.stateID="211013012" schoolEmployment.schoolNumber="200" individual.staffNumber="100981" individual.personID="733165" individual.gender="F" individual.suffix="" individual.middleName="" individual.firstName="Dyanne" individual.lastName="Fowler">
</person>
        <person 
        individual.alias="" pcontact.email="Justin.Franklin@jefferson.kyschools.us" individual.stateID="" schoolEmployment.schoolNumber="200" individual.staffNumber="122554" individual.personID="834163" individual.gender="M" individual.suffix="" individual.middleName="" individual.firstName="Justin" individual.lastName="Franklin">
</person>
        <person 
        individual.alias="" pcontact.email="Kathy.Fries@Jefferson.kyschools.us" individual.stateID="" schoolEmployment.schoolNumber="200" individual.staffNumber="103595" individual.personID="734570" individual.gender="M" individual.suffix="" individual.middleName="" individual.firstName="Kathryn" individual.lastName="Fries">
</person>
        <person 
        individual.alias="Lgallo1" pcontact.email="Lynette.Galloway@jefferson.kyschools.us" individual.stateID="" schoolEmployment.schoolNumber="200" individual.staffNumber="124450" individual.personID="744102" individual.gender="F" individual.suffix="" individual.middleName="M" individual.firstName="Lynette" individual.lastName="Galloway">
</person>
        <person 
        individual.alias="" pcontact.email="James.Garrett@Jefferson.kyschools.us" individual.stateID="211001479" schoolEmployment.schoolNumber="200" individual.staffNumber="110453" individual.personID="738237" individual.gender="M" individual.suffix="" individual.middleName="D" individual.firstName="James" individual.lastName="Garrett">
</person>
        <person 
        individual.alias="" pcontact.email="Kathleen.Geary@Jefferson.kyschools.us" individual.stateID="211003569" schoolEmployment.schoolNumber="200" individual.staffNumber="109620" individual.personID="737775" individual.gender="F" individual.suffix="" individual.middleName="" individual.firstName="Kathleen" individual.lastName="Geary">
</person>
        <person 
        individual.alias="" pcontact.email="Tim.Glasscock@Jefferson.kyschools.us" individual.stateID="211009431" schoolEmployment.schoolNumber="200" individual.staffNumber="113107" individual.personID="739646" individual.gender="M" individual.suffix="" individual.middleName="Timothy" individual.firstName="Samuel" individual.lastName="Glasscock">
</person>
        <person 
        individual.alias="" pcontact.email="Phyllis.Goff@Jefferson.kyschools.us" individual.stateID="211003053" schoolEmployment.schoolNumber="200" individual.staffNumber="114769" individual.personID="740526" individual.gender="F" individual.suffix="" individual.middleName="" individual.firstName="Phyllis" individual.lastName="Goff">
</person>
        <person 
        individual.alias="" pcontact.email="Gary.Gray@Jefferson.kyschools.us" individual.stateID="211009083" schoolEmployment.schoolNumber="200" individual.staffNumber="108791" individual.personID="737333" individual.gender="M" individual.suffix="" individual.middleName="" individual.firstName="Gary" individual.lastName="Gray">
</person>
        <person 
        individual.alias="" pcontact.email="" individual.stateID="" schoolEmployment.schoolNumber="200" individual.staffNumber="102764" individual.personID="935566" individual.gender="F" individual.suffix="" individual.middleName="H" individual.firstName="JOANNE" individual.lastName="GREAVER">
</person>
        <person 
        individual.alias="" pcontact.email="Jason.Gregory@Jefferson.kyschools.us" individual.stateID="" schoolEmployment.schoolNumber="200" individual.staffNumber="120036" individual.personID="742978" individual.gender="M" individual.suffix="" individual.middleName="" individual.firstName="Jason" individual.lastName="Gregory">
</person>
        <person 
        individual.alias="ngregor1" pcontact.email="NIKKI.GREGORY@JEFFERSON.KYSCHOOLS.US" individual.stateID="" schoolEmployment.schoolNumber="200" individual.staffNumber="119020" individual.personID="742776" individual.gender="F" individual.suffix="" individual.middleName="" individual.firstName="Nikki" individual.lastName="Gregory">
</person>
        <person 
        individual.alias="mgutier1" pcontact.email="marina.gutierrez@jefferson.kyschools.us" individual.stateID="211017335" schoolEmployment.schoolNumber="200" individual.staffNumber="117514" individual.personID="742030" individual.gender="F" individual.suffix="" individual.middleName="" individual.firstName="Marina" individual.lastName="Gutierrez">
</person>
        <person 
        individual.alias="Mhabic1" pcontact.email="megan.habich@jefferson.kyschools.us" individual.stateID="" schoolEmployment.schoolNumber="200" individual.staffNumber="128967" individual.personID="848012" individual.gender="F" individual.suffix="" individual.middleName="M" individual.firstName="Megan" individual.lastName="Habich">
</person>
        <person 
        individual.alias="" pcontact.email="Alice.Hall@Jefferson.kyschools.us" individual.stateID="211003591" schoolEmployment.schoolNumber="200" individual.staffNumber="115893" individual.personID="741135" individual.gender="F" individual.suffix="" individual.middleName="" individual.firstName="Alice" individual.lastName="Hall">
</person>
        <person 
        individual.alias="zhamri1" pcontact.email="Zachary.Hamric@jefferson.kyschools.us" individual.stateID="" schoolEmployment.schoolNumber="200" individual.staffNumber="129706" individual.personID="868240" individual.gender="M" individual.suffix="" individual.middleName="" individual.firstName="Zachary" individual.lastName="Hamric">
</person>
        <person 
        individual.alias="" pcontact.email="Jammie.Harper@Jefferson.kyschools.us" individual.stateID="" schoolEmployment.schoolNumber="200" individual.staffNumber="103014" individual.personID="734252" individual.gender="F" individual.suffix="" individual.middleName="" individual.firstName="Jammie" individual.lastName="Harper">
</person>
        <person 
        individual.alias="" pcontact.email="Leanne.Hartlage@jefferson.kyschools.us" individual.stateID="" schoolEmployment.schoolNumber="200" individual.staffNumber="109870" individual.personID="472131" individual.gender="F" individual.suffix="" individual.middleName="R" individual.firstName="Leanne" individual.lastName="Hartlage">
</person>
        <person 
        individual.alias="" pcontact.email="Peggy.Heimerdinger@Jefferson.kyschools.us" individual.stateID="211011586" schoolEmployment.schoolNumber="200" individual.staffNumber="117680" individual.personID="742125" individual.gender="F" individual.suffix="" individual.middleName="" individual.firstName="Peggy" individual.lastName="Heimerdinge R">
</person>
        <person 
        individual.alias="" pcontact.email="Kim.Herndon@Jefferson.kyschools.us" individual.stateID="1950517258" schoolEmployment.schoolNumber="200" individual.staffNumber="120049" individual.personID="742989" individual.gender="F" individual.suffix="" individual.middleName="L" individual.firstName="Kimberly" individual.lastName="Herndon">
</person>
        <person 
        individual.alias="" pcontact.email="Amy.Heskamp@Jefferson.kyschools.us" individual.stateID="211010940" schoolEmployment.schoolNumber="200" individual.staffNumber="107103" individual.personID="736433" individual.gender="F" individual.suffix="" individual.middleName="Sue" individual.firstName="Amy" individual.lastName="Heskamp">
</person>
        <person 
        individual.alias="" pcontact.email="janice.hibbs@jefferson.kyschools.us" individual.stateID="211014158" schoolEmployment.schoolNumber="200" individual.staffNumber="122357" individual.personID="743555" individual.gender="F" individual.suffix="" individual.middleName="" individual.firstName="Janice" individual.lastName="Hibbs">
</person>
        <person 
        individual.alias="" pcontact.email="charles.hill@jefferson.kyschools.us" individual.stateID="" schoolEmployment.schoolNumber="200" individual.staffNumber="100058" individual.personID="732661" individual.gender="M" individual.suffix="" individual.middleName="W" individual.firstName="Charles" individual.lastName="Hill">
</person>
        <person 
        individual.alias="" pcontact.email="david.hines@jefferson.kyschools.us" individual.stateID="211009965" schoolEmployment.schoolNumber="200" individual.staffNumber="110644" individual.personID="738344" individual.gender="M" individual.suffix="" individual.middleName="Samuel" individual.firstName="David" individual.lastName="Hines">
</person>
        <person 
        individual.alias="" pcontact.email="nachon.hobbs@jefferson.kyschools.us" individual.stateID="211011759" schoolEmployment.schoolNumber="200" individual.staffNumber="117461" individual.personID="541184" individual.gender="F" individual.suffix="" individual.middleName="C" individual.firstName="Nachon" individual.lastName="Hobbs">
</person>
        <person 
        individual.alias="" pcontact.email="gladys.hodges@jefferson.kyschools.us" individual.stateID="" schoolEmployment.schoolNumber="200" individual.staffNumber="" individual.personID="644976" individual.gender="F" individual.suffix="" individual.middleName="" individual.firstName="Gladys" individual.lastName="Hodges">
</person>
        <person 
        individual.alias="" pcontact.email="Tim.Holman@Jefferson.kyschools.us" individual.stateID="211006853" schoolEmployment.schoolNumber="200" individual.staffNumber="112631" individual.personID="739381" individual.gender="M" individual.suffix="" individual.middleName="" individual.firstName="Timothy" individual.lastName="Holman">
</person>
        <person 
        individual.alias="" pcontact.email="marilyn.holmes@jefferson.kyschools.us" individual.stateID="" schoolEmployment.schoolNumber="200" individual.staffNumber="105463" individual.personID="843415" individual.gender="F" individual.suffix="" individual.middleName="S" individual.firstName="Marilyn" individual.lastName="Holmes">
</person>
        <person 
        individual.alias="" pcontact.email="catherine.howle@jefferson.kyschools.us" individual.stateID="" schoolEmployment.schoolNumber="200" individual.staffNumber="127262" individual.personID="845071" individual.gender="F" individual.suffix="" individual.middleName="S" individual.firstName="Catherine" individual.lastName="Howle">
</person>
        <person 
        individual.alias="Lfield1" pcontact.email="Lori.Fields@VA.GOV" individual.stateID="" schoolEmployment.schoolNumber="200" individual.staffNumber="126261" individual.personID="301483" individual.gender="F" individual.suffix="" individual.middleName="F" individual.firstName="Lori" individual.lastName="Huffman">
</person>
        <person 
        individual.alias="Ahunt2" pcontact.email="allison.hunt@jefferson.kyschools.us" individual.stateID="2120167150" schoolEmployment.schoolNumber="200" individual.staffNumber="102858" individual.personID="748206" individual.gender="F" individual.suffix="" individual.middleName="M" individual.firstName="Allison" individual.lastName="Hunt">
</person>
        <person 
        individual.alias="" pcontact.email="Bill.Jackson@Jefferson.kyschools.us" individual.stateID="" schoolEmployment.schoolNumber="200" individual.staffNumber="100548" individual.personID="363741" individual.gender="M" individual.suffix="" individual.middleName="H" individual.firstName="Bill" individual.lastName="Jackson">
</person>
        <person 
        individual.alias="" pcontact.email="robert.jaffe@jefferson.kyschools.us" individual.stateID="211002288" schoolEmployment.schoolNumber="200" individual.staffNumber="108170" individual.personID="737010" individual.gender="M" individual.suffix="" individual.middleName="S" individual.firstName="Robert" individual.lastName="Jaffe">
</person>
        <person 
        individual.alias="" pcontact.email="louis.james2@jefferson.kyschools.us" individual.stateID="" schoolEmployment.schoolNumber="200" individual.staffNumber="129589" individual.personID="62264" individual.gender="M" individual.suffix="IV" individual.middleName="Henry" individual.firstName="Louis" individual.lastName="James">
</person>
        <person 
        individual.alias="" pcontact.email="Christian.Jensen@Jefferson.kyschools.us" individual.stateID="211015103" schoolEmployment.schoolNumber="200" individual.staffNumber="102188" individual.personID="733813" individual.gender="M" individual.suffix="" individual.middleName="" individual.firstName="Christian" individual.lastName="Jensen">
</person>
        <person 
        individual.alias="Sjohns13" pcontact.email="Shamika.Johnson@Jefferson.kyschools.us" individual.stateID="" schoolEmployment.schoolNumber="200" individual.staffNumber="121902" individual.personID="743489" individual.gender="F" individual.suffix="" individual.middleName="" individual.firstName="Shamika" individual.lastName="Johnson">
</person>
        <person 
        individual.alias="" pcontact.email="Marti.Johnston@jefferson.kyschools.us" individual.stateID="211014974" schoolEmployment.schoolNumber="200" individual.staffNumber="108613" individual.personID="737252" individual.gender="F" individual.suffix="" individual.middleName="Krista" individual.firstName="Marti" individual.lastName="Johnston">
</person>
        <person 
        individual.alias="" pcontact.email="Philip.Johnston@Jefferson.kyschools.us" individual.stateID="211017428" schoolEmployment.schoolNumber="200" individual.staffNumber="111633" individual.personID="738846" individual.gender="M" individual.suffix="" individual.middleName="" individual.firstName="Philip" individual.lastName="Johnston">
</person>
        <person 
        individual.alias="" pcontact.email="jeral.jordan@jefferson.kyschools.us" individual.stateID="211010331" schoolEmployment.schoolNumber="200" individual.staffNumber="114820" individual.personID="740554" individual.gender="M" individual.suffix="" individual.middleName="Mark" individual.firstName="Jeral" individual.lastName="Jordan">
</person>
        <person 
        individual.alias="" pcontact.email="James.Just@jefferson.kyschools.us" individual.stateID="211003382" schoolEmployment.schoolNumber="200" individual.staffNumber="117044" individual.personID="619280" individual.gender="F" individual.suffix="" individual.middleName="E" individual.firstName="James" individual.lastName="Just">
</person>
        <person 
        individual.alias="" pcontact.email="krista.just@jefferson.kyschools.us" individual.stateID="" schoolEmployment.schoolNumber="200" individual.staffNumber="131843" individual.personID="306741" individual.gender="F" individual.suffix="" individual.middleName="Ann" individual.firstName="Krista" individual.lastName="Just">
</person>
        <person 
        individual.alias="" pcontact.email="kajust@insightbb.com" individual.stateID="" schoolEmployment.schoolNumber="200" individual.staffNumber="131843" individual.personID="872209" individual.gender="F" individual.suffix="" individual.middleName="Ann" individual.firstName="Krista" individual.lastName="Just">
</person>
        <person 
        individual.alias="" pcontact.email="Thomas.Kalb@Jefferson.kyschools.us" individual.stateID="211010733" schoolEmployment.schoolNumber="200" individual.staffNumber="110450" individual.personID="738234" individual.gender="M" individual.suffix="" individual.middleName="" individual.firstName="Thomas" individual.lastName="Kalb">
</person>
        <person 
        individual.alias="" pcontact.email="Shannon.Kederis@jefferson.kyschools.us" individual.stateID="211007164" schoolEmployment.schoolNumber="200" individual.staffNumber="118336" individual.personID="742468" individual.gender="F" individual.suffix="" individual.middleName="" individual.firstName="Shannon" individual.lastName="Kederis">
</person>
        <person 
        individual.alias="" pcontact.email="beverly.keepers@jefferson.kyschools.us" individual.stateID="211016952" schoolEmployment.schoolNumber="200" individual.staffNumber="110626" individual.personID="738334" individual.gender="F" individual.suffix="" individual.middleName="" individual.firstName="Beverly" individual.lastName="Keepers">
</person>
        <person 
        individual.alias="" pcontact.email="Debby.Kennedy@Jefferson.kyschools.us" individual.stateID="211002111" schoolEmployment.schoolNumber="200" individual.staffNumber="104017" individual.personID="734806" individual.gender="F" individual.suffix="" individual.middleName="" individual.firstName="Deborah" individual.lastName="Kennedy">
</person>
        <person 
        individual.alias="" pcontact.email="Kristin.Kesler@jefferson.kyschools.us" individual.stateID="211004767" schoolEmployment.schoolNumber="200" individual.staffNumber="105809" individual.personID="419708" individual.gender="F" individual.suffix="" individual.middleName="A" individual.firstName="Kristin" individual.lastName="Kesler">
</person>
        <person 
        individual.alias="" pcontact.email="matt.kingsley@jefferson.kyschools.us" individual.stateID="" schoolEmployment.schoolNumber="200" individual.staffNumber="116895" individual.personID="690482" individual.gender="M" individual.suffix="" individual.middleName="D" individual.firstName="Matthew" individual.lastName="Kingsley">
</person>
        <person 
        individual.alias="" pcontact.email="marion.kirkpatrick@jefferson.kyschools.us" individual.stateID="2120283798" schoolEmployment.schoolNumber="200" individual.staffNumber="101114" individual.personID="755196" individual.gender="F" individual.suffix="" individual.middleName="A" individual.firstName="Marion" individual.lastName="Kirkpatrick">
</person>
        <person 
        individual.alias="" pcontact.email="Georgette.Kleier-Hott@jefferson.kyschools.us" individual.stateID="" schoolEmployment.schoolNumber="200" individual.staffNumber="103435" individual.personID="734481" individual.gender="F" individual.suffix="" individual.middleName="" individual.firstName="Georgette" individual.lastName="Kleier-Hottois">
</person>
        <person 
        individual.alias="rkraus2" pcontact.email="raymund.krause@jefferson.kyschools.us" individual.stateID="" schoolEmployment.schoolNumber="200" individual.staffNumber="132616" individual.personID="917013" individual.gender="M" individual.suffix="" individual.middleName="Jon" individual.firstName="Raymund" individual.lastName="Krause">
</person>
        <person 
        individual.alias="" pcontact.email="John.Krysinski@jefferson.kyschools.us" individual.stateID="211004926" schoolEmployment.schoolNumber="200" individual.staffNumber="105886" individual.personID="735794" individual.gender="M" individual.suffix="" individual.middleName="M" individual.firstName="John" individual.lastName="Krysinski">
</person>
        <person 
        individual.alias="Gkuhn2" pcontact.email="Greg.Kuhn@Jefferson.kyschools.us" individual.stateID="211001748" schoolEmployment.schoolNumber="200" individual.staffNumber="101741" individual.personID="733563" individual.gender="M" individual.suffix="" individual.middleName="S" individual.firstName="Gregory" individual.lastName="Kuhn">
</person>
        <person 
        individual.alias="" pcontact.email="Venetia.Lacy@Jefferson.kyschools.us" individual.stateID="211004007" schoolEmployment.schoolNumber="200" individual.staffNumber="100499" individual.personID="732889" individual.gender="F" individual.suffix="" individual.middleName="E" individual.firstName="Venetia" individual.lastName="Lacy">
</person>
        <person 
        individual.alias="" pcontact.email="Dawn.Lader@Jefferson.kyschools.us" individual.stateID="211005770" schoolEmployment.schoolNumber="200" individual.staffNumber="118763" individual.personID="742694" individual.gender="F" individual.suffix="" individual.middleName="" individual.firstName="Dawn" individual.lastName="Lader">
</person>
        <person 
        individual.alias="clampto1" pcontact.email="Cindy.Lampton@jefferson.kyschools.us" individual.stateID="211002703" schoolEmployment.schoolNumber="200" individual.staffNumber="116254" individual.personID="741327" individual.gender="F" individual.suffix="" individual.middleName="" individual.firstName="Cynthia" individual.lastName="Lampton">
</person>
        <person 
        individual.alias="" pcontact.email="marilyn.lawless@jefferson.kyschools.us" individual.stateID="211004379" schoolEmployment.schoolNumber="200" individual.staffNumber="104234" individual.personID="734927" individual.gender="F" individual.suffix="" individual.middleName="A" individual.firstName="Marilyn" individual.lastName="Lawless">
</person>
        <person 
        individual.alias="" pcontact.email="Mary.Braun@jefferson.kyschools.us" individual.stateID="211003238" schoolEmployment.schoolNumber="200" individual.staffNumber="108354" individual.personID="737110" individual.gender="F" individual.suffix="" individual.middleName="Kathryn" individual.firstName="Mary" individual.lastName="Lenihan">
</person>
        <person 
        individual.alias="" pcontact.email="John.Lewis@jefferson.kyschools.us" individual.stateID="2120284008" schoolEmployment.schoolNumber="200" individual.staffNumber="127641" individual.personID="821733" individual.gender="M" individual.suffix="" individual.middleName="R" individual.firstName="John" individual.lastName="Lewis">
</person>
        <person 
        individual.alias="" pcontact.email="Danna.Livers@Jefferson.kyschools.us" individual.stateID="211006253" schoolEmployment.schoolNumber="200" individual.staffNumber="101842" individual.personID="733626" individual.gender="F" individual.suffix="" individual.middleName="" individual.firstName="Danna" individual.lastName="Livers">
</person>
        <person 
        individual.alias="" pcontact.email="Patrice.Lowe@Jefferson.kyschools.us" individual.stateID="211005643" schoolEmployment.schoolNumber="200" individual.staffNumber="120258" individual.personID="743134" individual.gender="F" individual.suffix="" individual.middleName="S" individual.firstName="Patrice" individual.lastName="Lowe">
</person>
        <person 
        individual.alias="" pcontact.email="oliver.lucas@jefferson.kyschools.us" individual.stateID="" schoolEmployment.schoolNumber="200" individual.staffNumber="131282" individual.personID="897220" individual.gender="M" individual.suffix="" individual.middleName="" individual.firstName="Oliver" individual.lastName="Lucas">
</person>
        <person 
        individual.alias="Mlyons1" pcontact.email="Mary.Lyons2@jefferson.kyschools.us" individual.stateID="211016881" schoolEmployment.schoolNumber="200" individual.staffNumber="107291" individual.personID="736549" individual.gender="F" individual.suffix="" individual.middleName="E" individual.firstName="Mary" individual.lastName="Lyons">
</person>
        <person 
        individual.alias="" pcontact.email="steven.makela@jefferson.kyschools.us" individual.stateID="211010812" schoolEmployment.schoolNumber="200" individual.staffNumber="105734" individual.personID="735708" individual.gender="M" individual.suffix="" individual.middleName="K" individual.firstName="Steven" individual.lastName="Makela">
</person>
        <person 
        individual.alias="Cmccar32" pcontact.email="Cynthia.McCarty@Jefferson.kyschools.us" individual.stateID="211016487" schoolEmployment.schoolNumber="200" individual.staffNumber="112083" individual.personID="739085" individual.gender="F" individual.suffix="" individual.middleName="L" individual.firstName="Cynthia" individual.lastName="McCarty">
</person>
        <person 
        individual.alias="" pcontact.email="joseph.mcdaniel@jefferson.kyschools.us" individual.stateID="211002248" schoolEmployment.schoolNumber="200" individual.staffNumber="104218" individual.personID="734917" individual.gender="M" individual.suffix="" individual.middleName="P" individual.firstName="Joseph" individual.lastName="McDaniel">
</person>
        <person 
        individual.alias="rmcfall2" pcontact.email="Ros.McFall@Jefferson.kyschools.us" individual.stateID="211014574" schoolEmployment.schoolNumber="200" individual.staffNumber="106330" individual.personID="736036" individual.gender="F" individual.suffix="" individual.middleName="N" individual.firstName="Rosalind" individual.lastName="McFall">
</person>
        <person 
        individual.alias="" pcontact.email="carrie.mckeehan@jefferson.kyschools.us" individual.stateID="" schoolEmployment.schoolNumber="200" individual.staffNumber="123599" individual.personID="883562" individual.gender="F" individual.suffix="" individual.middleName="Marie" individual.firstName="Carrie" individual.lastName="McKeehan">
</person>
        <person 
        individual.alias="" pcontact.email="Diane.McKim@Jefferson.kyschools.us" individual.stateID="211003212" schoolEmployment.schoolNumber="200" individual.staffNumber="105532" individual.personID="735593" individual.gender="F" individual.suffix="" individual.middleName="" individual.firstName="Patricia" individual.lastName="McKim">
</person>
        <person 
        individual.alias="" pcontact.email="paul.mckim@jefferson.kyschools.us" individual.stateID="211013750" schoolEmployment.schoolNumber="200" individual.staffNumber="104059" individual.personID="734829" individual.gender="M" individual.suffix="" individual.middleName="J" individual.firstName="Paul" individual.lastName="McKim">
</person>
        <person 
        individual.alias="" pcontact.email="joanna.mclemore@jefferson.kyschools.us" individual.stateID="" schoolEmployment.schoolNumber="200" individual.staffNumber="110119" individual.personID="738062" individual.gender="F" individual.suffix="" individual.middleName="" individual.firstName="Joanna" individual.lastName="McLemore">
</person>
        <person 
        individual.alias="" pcontact.email="Amy.Medley@Jefferson.kyschools.us" individual.stateID="" schoolEmployment.schoolNumber="200" individual.staffNumber="119880" individual.personID="742924" individual.gender="F" individual.suffix="" individual.middleName="P" individual.firstName="Amy" individual.lastName="Medley">
</person>
        <person 
        individual.alias="" pcontact.email="Camille.Medley@Jefferson.kyschools.us" individual.stateID="211014934" schoolEmployment.schoolNumber="200" individual.staffNumber="100757" individual.personID="733033" individual.gender="F" individual.suffix="" individual.middleName="" individual.firstName="Camille" individual.lastName="Medley">
</person>
        <person 
        individual.alias="bmeng1" pcontact.email="Beverley.Meng@jefferson.kyschools.us" individual.stateID="211012981" schoolEmployment.schoolNumber="200" individual.staffNumber="123972" individual.personID="744035" individual.gender="F" individual.suffix="" individual.middleName="S" individual.firstName="Beverley" individual.lastName="Meng">
</person>
        <person 
        individual.alias="Cmerten1" pcontact.email="Cheryl.Merten@Jefferson.kyschools.us" individual.stateID="211010200" schoolEmployment.schoolNumber="200" individual.staffNumber="111611" individual.personID="738834" individual.gender="F" individual.suffix="" individual.middleName="" individual.firstName="Cheryl" individual.lastName="Merten">
</person>
        <person 
        individual.alias="" pcontact.email="Susan.Mike@Jefferson.kyschools.us" individual.stateID="211010620" schoolEmployment.schoolNumber="200" individual.staffNumber="105842" individual.personID="735763" individual.gender="F" individual.suffix="" individual.middleName="S" individual.firstName="Carolyn" individual.lastName="Mike">
</person>
        <person 
        individual.alias="" pcontact.email="James.Miller@Jefferson.kyschools.us" individual.stateID="211006338" schoolEmployment.schoolNumber="200" individual.staffNumber="100704" individual.personID="733007" individual.gender="M" individual.suffix="Jr." individual.middleName="H" individual.firstName="James" individual.lastName="Miller">
</person>
        <person 
        individual.alias="Rminee1" pcontact.email="Robert.Mineer@jefferson.kyschools.us" individual.stateID="" schoolEmployment.schoolNumber="200" individual.staffNumber="128095" individual.personID="882865" individual.gender="M" individual.suffix="" individual.middleName="" individual.firstName="Rob" individual.lastName="Mineer">
</person>
        <person 
        individual.alias="" pcontact.email="debra.moore@jefferson.kyschools.us" individual.stateID="211012404" schoolEmployment.schoolNumber="200" individual.staffNumber="115847" individual.personID="741111" individual.gender="F" individual.suffix="" individual.middleName="J" individual.firstName="Debra" individual.lastName="Moore">
</person>
        <person 
        individual.alias="" pcontact.email="Katherine.Morgan@Jefferson.kyschools.us" individual.stateID="2120171390" schoolEmployment.schoolNumber="200" individual.staffNumber="114553" individual.personID="758604" individual.gender="F" individual.suffix="" individual.middleName="E" individual.firstName="Katherine" individual.lastName="Morgan">
</person>
        <person 
        individual.alias="" pcontact.email="Daniel.Morgan@Jefferson.kyschools.us" individual.stateID="211002432" schoolEmployment.schoolNumber="200" individual.staffNumber="108340" individual.personID="737104" individual.gender="M" individual.suffix="" individual.middleName="" individual.firstName="R Daniel" individual.lastName="Morgan">
</person>
        <person 
        individual.alias="" pcontact.email="erin.moss@jefferson.kyschools.us" individual.stateID="2120167160" schoolEmployment.schoolNumber="200" individual.staffNumber="125035" individual.personID="748207" individual.gender="F" individual.suffix="" individual.middleName="M" individual.firstName="Erin" individual.lastName="Moss">
</person>
        <person 
        individual.alias="" pcontact.email="Mick.Motley@jefferson.kyschools.us" individual.stateID="211009835" schoolEmployment.schoolNumber="200" individual.staffNumber="122150" individual.personID="743527" individual.gender="M" individual.suffix="" individual.middleName="A" individual.firstName="Michael" individual.lastName="Motley">
</person>
        <person 
        individual.alias="" pcontact.email="Theresa.Mudd-Kelly@jefferson.kyschools.us" individual.stateID="211010288" schoolEmployment.schoolNumber="200" individual.staffNumber="114689" individual.personID="740489" individual.gender="F" individual.suffix="" individual.middleName="" individual.firstName="Theresa" individual.lastName="Mudd">
</person>
        <person 
        individual.alias="" pcontact.email="Stefan.Muller@Jefferson.kyschools.us" individual.stateID="211007157" schoolEmployment.schoolNumber="200" individual.staffNumber="109985" individual.personID="737986" individual.gender="M" individual.suffix="" individual.middleName="" individual.firstName="Stefan" individual.lastName="Muller">
</person>
        <person 
        individual.alias="" pcontact.email="veronica.munn@jefferson.kyschools.us" individual.stateID="" schoolEmployment.schoolNumber="200" individual.staffNumber="103854" individual.personID="734713" individual.gender="F" individual.suffix="" individual.middleName="" individual.firstName="Veronica" individual.lastName="Munn">
</person>
        <person 
        individual.alias="" pcontact.email="Tim.Murner@Jefferson.kyschools.us" individual.stateID="211015619" schoolEmployment.schoolNumber="200" individual.staffNumber="110358" individual.personID="738189" individual.gender="M" individual.suffix="" individual.middleName="" individual.firstName="Tim" individual.lastName="Murner">
</person>
        <person 
        individual.alias="" pcontact.email="bobby.murphy@jefferson.kyschools.us" individual.stateID="2120167170" schoolEmployment.schoolNumber="200" individual.staffNumber="125129" individual.personID="748208" individual.gender="M" individual.suffix="" individual.middleName="G" individual.firstName="Bobby" individual.lastName="Murphy">
</person>
        <person 
        individual.alias="" pcontact.email="Jason.Neuss@Jefferson.kyschools.us" individual.stateID="211007726" schoolEmployment.schoolNumber="200" individual.staffNumber="117211" individual.personID="741853" individual.gender="M" individual.suffix="" individual.middleName="" individual.firstName="Jason" individual.lastName="Neuss">
</person>
        <person 
        individual.alias="" pcontact.email="Joe.Nichols@Jefferson.kyschools.us" individual.stateID="211014957" schoolEmployment.schoolNumber="200" individual.staffNumber="102177" individual.personID="733806" individual.gender="M" individual.suffix="" individual.middleName="" individual.firstName="Joseph" individual.lastName="Nichols">
</person>
        <person 
        individual.alias="" pcontact.email="Jane.Norman@Jefferson.kyschools.us" individual.stateID="211003997" schoolEmployment.schoolNumber="200" individual.staffNumber="105570" individual.personID="735613" individual.gender="F" individual.suffix="" individual.middleName="" individual.firstName="Jane" individual.lastName="Norman">
</person>
        <person 
        individual.alias="" pcontact.email="Todd.Obryan@jefferson.kyschools.us" individual.stateID="211001173" schoolEmployment.schoolNumber="200" individual.staffNumber="106361" individual.personID="736052" individual.gender="M" individual.suffix="" individual.middleName="" individual.firstName="Todd" individual.lastName="O'Bryan">
</person>
        <person 
        individual.alias="" pcontact.email="Edward.Obryan@jefferson.kyschools.us" individual.stateID="211011179" schoolEmployment.schoolNumber="200" individual.staffNumber="100998" individual.personID="733178" individual.gender="M" individual.suffix="" individual.middleName="" individual.firstName="Edward" individual.lastName="Obryan">
</person>
        <person 
        individual.alias="" pcontact.email="patricia.padgett@jefferson.kyschools.us" individual.stateID="" schoolEmployment.schoolNumber="200" individual.staffNumber="131132" individual.personID="904407" individual.gender="F" individual.suffix="" individual.middleName="Lynn" individual.firstName="Patricia" individual.lastName="Padgett">
</person>
        <person 
        individual.alias="epalmer1" pcontact.email="liz.palmer@jefferson.kyschools.us" individual.stateID="211008615" schoolEmployment.schoolNumber="200" individual.staffNumber="111589" individual.personID="738824" individual.gender="F" individual.suffix="" individual.middleName="A" individual.firstName="Elizabeth" individual.lastName="Palmer">
</person>
        <person 
        individual.alias="" pcontact.email="Ruth.Pascualborq@jefferson.kyschools.us" individual.stateID="211001135" schoolEmployment.schoolNumber="200" individual.staffNumber="100709" individual.personID="733009" individual.gender="F" individual.suffix="" individual.middleName="" individual.firstName="Ruth" individual.lastName="Pascualborq Uez">
</person>
        <person 
        individual.alias="" pcontact.email="Sharon.Pass@Jefferson.kyschools.us" individual.stateID="211015217" schoolEmployment.schoolNumber="200" individual.staffNumber="100341" individual.personID="732807" individual.gender="F" individual.suffix="" individual.middleName="" individual.firstName="Sharon" individual.lastName="Pass">
</person>
        <person 
        individual.alias="" pcontact.email="loretta.pelc@jefferson.kyschools.us" individual.stateID="211005439" schoolEmployment.schoolNumber="200" individual.staffNumber="117559" individual.personID="742053" individual.gender="F" individual.suffix="" individual.middleName="E" individual.firstName="Loretta" individual.lastName="Pelc">
</person>
        <person 
        individual.alias="" pcontact.email="Stacy.Pendleton@Jefferson.kyschools.us" individual.stateID="" schoolEmployment.schoolNumber="200" individual.staffNumber="107558" individual.personID="736690" individual.gender="M" individual.suffix="" individual.middleName="" individual.firstName="Stacy" individual.lastName="Pendleton">
</person>
        <person 
        individual.alias="" pcontact.email="connie.pendygraft@jefferson.kyschools.us" individual.stateID="211006901" schoolEmployment.schoolNumber="200" individual.staffNumber="109421" individual.personID="737677" individual.gender="F" individual.suffix="" individual.middleName="C" individual.firstName="Mary" individual.lastName="Pendygraft">
</person>
        <person 
        individual.alias="" pcontact.email="Ralph.Pendygraft@jefferson.kyschools.us" individual.stateID="211002919" schoolEmployment.schoolNumber="200" individual.staffNumber="123012" individual.personID="743896" individual.gender="M" individual.suffix="" individual.middleName="" individual.firstName="Ralph" individual.lastName="Pendygraft">
</person>
        <person 
        individual.alias="" pcontact.email="Joan.Perkins@Jefferson.kyschools.us" individual.stateID="211006727" schoolEmployment.schoolNumber="200" individual.staffNumber="105998" individual.personID="735851" individual.gender="F" individual.suffix="" individual.middleName="" individual.firstName="Joan" individual.lastName="Perkins">
</person>
        <person 
        individual.alias="" pcontact.email="mark.pickering@jefferson.kyschools.us" individual.stateID="2120167180" schoolEmployment.schoolNumber="200" individual.staffNumber="125140" individual.personID="748209" individual.gender="M" individual.suffix="" individual.middleName="J" individual.firstName="Mark" individual.lastName="Pickering">
</person>
        <person 
        individual.alias="" pcontact.email="Ren.Pittman@Jefferson.kyschools.us" individual.stateID="211013109" schoolEmployment.schoolNumber="200" individual.staffNumber="117657" individual.personID="742107" individual.gender="M" individual.suffix="" individual.middleName="D" individual.firstName="Ren" individual.lastName="Pittman">
</person>
        <person 
        individual.alias="" pcontact.email="Mary.Plappert@jefferson.kyschools.us" individual.stateID="211013981" schoolEmployment.schoolNumber="200" individual.staffNumber="102874" individual.personID="734181" individual.gender="F" individual.suffix="" individual.middleName="" individual.firstName="Mary" individual.lastName="Plappert">
</person>
        <person 
        individual.alias="" pcontact.email="Debbie.Popham@Jefferson.kyschools.us" individual.stateID="211013303" schoolEmployment.schoolNumber="200" individual.staffNumber="106492" individual.personID="736124" individual.gender="F" individual.suffix="" individual.middleName="L" individual.firstName="Debra" individual.lastName="Popham">
</person>
        <person 
        individual.alias="" pcontact.email="david.prior@jefferson.kyschools.us" individual.stateID="211011700" schoolEmployment.schoolNumber="200" individual.staffNumber="103178" individual.personID="734340" individual.gender="M" individual.suffix="" individual.middleName="A" individual.firstName="David" individual.lastName="Prior">
</person>
        <person 
        individual.alias="" pcontact.email="Eric.Purvis@Jefferson.kyschools.us" individual.stateID="" schoolEmployment.schoolNumber="200" individual.staffNumber="113576" individual.personID="739903" individual.gender="M" individual.suffix="" individual.middleName="" individual.firstName="Eric" individual.lastName="Purvis">
</person>
        <person 
        individual.alias="" pcontact.email="shirley.pyles@jefferson.kyschools.us" individual.stateID="211007631" schoolEmployment.schoolNumber="200" individual.staffNumber="106563" individual.personID="736153" individual.gender="F" individual.suffix="" individual.middleName="A" individual.firstName="Shirley" individual.lastName="Pyles">
</person>
        <person 
        individual.alias="" pcontact.email="Greg.Rash@Jefferson.kyschools.us" individual.stateID="211003865" schoolEmployment.schoolNumber="200" individual.staffNumber="100327" individual.personID="732797" individual.gender="M" individual.suffix="" individual.middleName="" individual.firstName="Gregory" individual.lastName="Rash">
</person>
        <person 
        individual.alias="" pcontact.email="JC.Reedy@Jefferson.kyschools.us" individual.stateID="211009205" schoolEmployment.schoolNumber="200" individual.staffNumber="108214" individual.personID="737030" individual.gender="M" individual.suffix="" individual.middleName="" individual.firstName="John" individual.lastName="Reedy">
</person>
        <person 
        individual.alias="" pcontact.email="leanne.repper@jefferson.kyschools.us" individual.stateID="" schoolEmployment.schoolNumber="200" individual.staffNumber="128143" individual.personID="835490" individual.gender="F" individual.suffix="" individual.middleName="Leanne" individual.firstName="Sally" individual.lastName="Repper">
</person>
        <person 
        individual.alias="" pcontact.email="Alexis.Rich@Jefferson.kyschools.us" individual.stateID="" schoolEmployment.schoolNumber="200" individual.staffNumber="117909" individual.personID="742257" individual.gender="F" individual.suffix="" individual.middleName="" individual.firstName="Alexis" individual.lastName="Rich">
</person>
        <person 
        individual.alias="" pcontact.email="russell.rigdon@jefferson.kyschools.us" individual.stateID="2120281741" schoolEmployment.schoolNumber="200" individual.staffNumber="131670" individual.personID="904409" individual.gender="M" individual.suffix="" individual.middleName="C" individual.firstName="Russell" individual.lastName="Rigdon">
</person>
        <person 
        individual.alias="" pcontact.email="Barbara.Risner@Jefferson.kyschools.us" individual.stateID="211012376" schoolEmployment.schoolNumber="200" individual.staffNumber="104382" individual.personID="735003" individual.gender="F" individual.suffix="" individual.middleName="" individual.firstName="Barbara" individual.lastName="Risner">
</person>
        <person 
        individual.alias="" pcontact.email="Brenda.Risner@jefferson.kyschools.us" individual.stateID="211016413" schoolEmployment.schoolNumber="200" individual.staffNumber="101022" individual.personID="733193" individual.gender="F" individual.suffix="" individual.middleName="" individual.firstName="Brenda" individual.lastName="Risner">
</person>
        <person 
        individual.alias="" pcontact.email="amy.ritchie@jefferson.kyschools.us" individual.stateID="211016637" schoolEmployment.schoolNumber="200" individual.staffNumber="101979" individual.personID="733697" individual.gender="F" individual.suffix="" individual.middleName="Beth" individual.firstName="Amy" individual.lastName="Ritchie">
</person>
        <person 
        individual.alias="" pcontact.email="Dennis.Robinson@Jefferson.kyschools.us" individual.stateID="211004584" schoolEmployment.schoolNumber="200" individual.staffNumber="118434" individual.personID="742511" individual.gender="M" individual.suffix="" individual.middleName="Shea" individual.firstName="Dennis" individual.lastName="Robinson">
</person>
        <person 
        individual.alias="" pcontact.email="Merritt.Robinson@Jefferson.kyschools.us" individual.stateID="211010393" schoolEmployment.schoolNumber="200" individual.staffNumber="115148" individual.personID="740734" individual.gender="F" individual.suffix="" individual.middleName="" individual.firstName="Merritt" individual.lastName="Robinson">
</person>
        <person 
        individual.alias="" pcontact.email="chester.rock@jefferson.kyschools.us" individual.stateID="2120252756" schoolEmployment.schoolNumber="200" individual.staffNumber="126633" individual.personID="797169" individual.gender="M" individual.suffix="" individual.middleName="C" individual.firstName="Chester" individual.lastName="Rock">
</person>
        <person 
        individual.alias="" pcontact.email="carey.rothbauer@jefferson.kyschools.us" individual.stateID="211014307" schoolEmployment.schoolNumber="200" individual.staffNumber="129150" individual.personID="744150" individual.gender="M" individual.suffix="" individual.middleName="L" individual.firstName="Carey" individual.lastName="Rothbauer">
</person>
        <person 
        individual.alias="" pcontact.email="Gary.Rushin@Jefferson.kyschools.us" individual.stateID="211005202" schoolEmployment.schoolNumber="200" individual.staffNumber="107256" individual.personID="736532" individual.gender="M" individual.suffix="" individual.middleName="" individual.firstName="Gary" individual.lastName="Rushin">
</person>
        <person 
        individual.alias="" pcontact.email="Lora.Ruttan@jefferson.kyschools.us" individual.stateID="" schoolEmployment.schoolNumber="200" individual.staffNumber="129885" individual.personID="867571" individual.gender="F" individual.suffix="" individual.middleName="" individual.firstName="Lora" individual.lastName="Ruttan">
</person>
        <person 
        individual.alias="" pcontact.email="brian.sakseski@jefferson.kyschools.us" individual.stateID="211008808" schoolEmployment.schoolNumber="200" individual.staffNumber="104141" individual.personID="734872" individual.gender="M" individual.suffix="" individual.middleName="K" individual.firstName="Brian" individual.lastName="Saksefski">
</person>
        <person 
        individual.alias="" pcontact.email="Tim.Salkeld@Jefferson.kyschools.us" individual.stateID="211008670" schoolEmployment.schoolNumber="200" individual.staffNumber="111939" individual.personID="739009" individual.gender="M" individual.suffix="" individual.middleName="" individual.firstName="Timothy" individual.lastName="Salkeld">
</person>
        <person 
        individual.alias="" pcontact.email="Rebecca.Samson@jefferson.kyschools.us" individual.stateID="211007669" schoolEmployment.schoolNumber="200" individual.staffNumber="107024" individual.personID="736387" individual.gender="F" individual.suffix="" individual.middleName="Carol" individual.firstName="Rebecca" individual.lastName="Samson">
</person>
        <person 
        individual.alias="Asander3" pcontact.email="Anita.Sanders@Jefferson.kyschools.us" individual.stateID="211004318" schoolEmployment.schoolNumber="200" individual.staffNumber="110028" individual.personID="738011" individual.gender="F" individual.suffix="" individual.middleName="L" individual.firstName="Anita" individual.lastName="Sanders">
</person>
        <person 
        individual.alias="" pcontact.email="Carole.Sanders@Jefferson.kyschools.us" individual.stateID="211006194" schoolEmployment.schoolNumber="200" individual.staffNumber="117853" individual.personID="742230" individual.gender="F" individual.suffix="" individual.middleName="" individual.firstName="Carole" individual.lastName="Sanders">
</person>
        <person 
        individual.alias="" pcontact.email="thea.sanders@jefferson.kyschools.us" individual.stateID="211010012" schoolEmployment.schoolNumber="200" individual.staffNumber="105146" individual.personID="735407" individual.gender="F" individual.suffix="" individual.middleName="Marie" individual.firstName="Thea" individual.lastName="Sanders">
</person>
        <person 
        individual.alias="Lsaylor1" pcontact.email="Lisa.Saylor@Jefferson.kyschools.us" individual.stateID="" schoolEmployment.schoolNumber="200" individual.staffNumber="101651" individual.personID="408474" individual.gender="F" individual.suffix="" individual.middleName="" individual.firstName="Lisa" individual.lastName="Saylor">
</person>
        <person 
        individual.alias="" pcontact.email="Carlton.Schackert@Jefferson.kyschools.us" individual.stateID="211012335" schoolEmployment.schoolNumber="200" individual.staffNumber="104287" individual.personID="734955" individual.gender="M" individual.suffix="" individual.middleName="" individual.firstName="Carlton" individual.lastName="Schackert">
</person>
        <person 
        individual.alias="" pcontact.email="Beth.Schaefer@Jefferson.kyschools.us" individual.stateID="211006293" schoolEmployment.schoolNumber="200" individual.staffNumber="113536" individual.personID="739881" individual.gender="F" individual.suffix="" individual.middleName="" individual.firstName="Beth" individual.lastName="Schaefer">
</person>
        <person 
        individual.alias="" pcontact.email="Robert.Schroeder@jefferson.kyschools.us" individual.stateID="211003316" schoolEmployment.schoolNumber="200" individual.staffNumber="108627" individual.personID="737260" individual.gender="M" individual.suffix="" individual.middleName="" individual.firstName="Robert" individual.lastName="Schroeder">
</person>
        <person 
        individual.alias="" pcontact.email="Betty.Schuetter@Jefferson.kyschools.us" individual.stateID="211015587" schoolEmployment.schoolNumber="200" individual.staffNumber="110002" individual.personID="737996" individual.gender="F" individual.suffix="" individual.middleName="" individual.firstName="Betty" individual.lastName="Schuetter">
</person>
        <person 
        individual.alias="" pcontact.email="JohnPaul.Schuster@Jefferson.kyschools.us" individual.stateID="211002312" schoolEmployment.schoolNumber="200" individual.staffNumber="103444" individual.personID="734486" individual.gender="M" individual.suffix="" individual.middleName="" individual.firstName="John" individual.lastName="Schuster">
</person>
        <person 
        individual.alias="" pcontact.email="Jason.Seber@jefferson.kyschools.us" individual.stateID="" schoolEmployment.schoolNumber="200" individual.staffNumber="122685" individual.personID="743669" individual.gender="M" individual.suffix="" individual.middleName="" individual.firstName="Jason" individual.lastName="Seber">
</person>
        <person 
        individual.alias="rsharp2" pcontact.email="Richard.Sharp@jefferson.kyschools.us" individual.stateID="" schoolEmployment.schoolNumber="200" individual.staffNumber="125121" individual.personID="744229" individual.gender="M" individual.suffix="" individual.middleName="A" individual.firstName="Richard" individual.lastName="Sharp">
</person>
        <person 
        individual.alias="" pcontact.email="Suzanne.Sidebottom@Jefferson.kyschools.us" individual.stateID="211012026" schoolEmployment.schoolNumber="200" individual.staffNumber="110491" individual.personID="738260" individual.gender="F" individual.suffix="" individual.middleName="" individual.firstName="Suzanne" individual.lastName="Sidebottom">
</person>
        <person 
        individual.alias="" pcontact.email="alonna.sitter@jefferson.kyschools.us" individual.stateID="211014819" schoolEmployment.schoolNumber="200" individual.staffNumber="109045" individual.personID="737464" individual.gender="F" individual.suffix="" individual.middleName="G" individual.firstName="Alonna" individual.lastName="Sitter">
</person>
        <person 
        individual.alias="" pcontact.email="Tim.Smith@Jefferson.kyschools.us" individual.stateID="211013931" schoolEmployment.schoolNumber="200" individual.staffNumber="108264" individual.personID="737056" individual.gender="M" individual.suffix="" individual.middleName="" individual.firstName="Timothy" individual.lastName="Smith">
</person>
        <person 
        individual.alias="" pcontact.email="debroah.smith-gib@jefferson.kyschools.us" individual.stateID="2120247304" schoolEmployment.schoolNumber="200" individual.staffNumber="126682" individual.personID="789864" individual.gender="F" individual.suffix="" individual.middleName="E" individual.firstName="Deborah" individual.lastName="Smith-Gibson">
</person>
        <person 
        individual.alias="" pcontact.email="Mary.Sowers@jefferson.kyschools.us" individual.stateID="211013801" schoolEmployment.schoolNumber="200" individual.staffNumber="111348" individual.personID="738711" individual.gender="F" individual.suffix="" individual.middleName="" individual.firstName="Mary" individual.lastName="Sowers">
</person>
        <person 
        individual.alias="" pcontact.email="Laura.Spiegelhalt@jefferson.kyschools.us" individual.stateID="211006397" schoolEmployment.schoolNumber="200" individual.staffNumber="116400" individual.personID="741403" individual.gender="F" individual.suffix="" individual.middleName="B" individual.firstName="Laura" individual.lastName="Spiegelhalter">
</person>
        <person 
        individual.alias="" pcontact.email="warren.stanley@jefferson.kyschools.us" individual.stateID="" schoolEmployment.schoolNumber="200" individual.staffNumber="112663" individual.personID="835844" individual.gender="M" individual.suffix="" individual.middleName="" individual.firstName="Warren" individual.lastName="Stanley">
</person>
        <person 
        individual.alias="" pcontact.email="Sharon.Stefater@Jefferson.kyschools.us" individual.stateID="211016303" schoolEmployment.schoolNumber="200" individual.staffNumber="114514" individual.personID="740390" individual.gender="F" individual.suffix="" individual.middleName="" individual.firstName="Sharon" individual.lastName="Stefater">
</person>
        <person 
        individual.alias="" pcontact.email="Lisa.Stevenson1@Jefferson.kyschools.us" individual.stateID="211003841" schoolEmployment.schoolNumber="200" individual.staffNumber="111442" individual.personID="738755" individual.gender="F" individual.suffix="" individual.middleName="" individual.firstName="Lisa" individual.lastName="Stevenson">
</person>
        <person 
        individual.alias="" pcontact.email="Patrick.Stevenson@Jefferson.kyschools.us" individual.stateID="211001005" schoolEmployment.schoolNumber="200" individual.staffNumber="104390" individual.personID="735007" individual.gender="M" individual.suffix="" individual.middleName="" individual.firstName="Patrick" individual.lastName="Stevenson">
</person>
        <person 
        individual.alias="" pcontact.email="Beth.Stottman@Jefferson.kyschools.us" individual.stateID="211007978" schoolEmployment.schoolNumber="200" individual.staffNumber="104333" individual.personID="734978" individual.gender="F" individual.suffix="" individual.middleName="M" individual.firstName="Beth" individual.lastName="Stottman">
</person>
        <person 
        individual.alias="" pcontact.email="Earl.Stoudemire@Jefferson.kyschools.us" individual.stateID="211006479" schoolEmployment.schoolNumber="200" individual.staffNumber="105707" individual.personID="735698" individual.gender="M" individual.suffix="" individual.middleName="" individual.firstName="Earl" individual.lastName="Stoudemire Jr">
</person>
        <person 
        individual.alias="" pcontact.email="ImaLori.Strohmayer@jefferson.kyschools.us" individual.stateID="" schoolEmployment.schoolNumber="200" individual.staffNumber="122870" individual.personID="743819" individual.gender="F" individual.suffix="" individual.middleName="" individual.firstName="Lori" individual.lastName="Strohmayer">
</person>
        <person 
        individual.alias="" pcontact.email="janice.strothoff@jefferson.kyschools.us" individual.stateID="211016994" schoolEmployment.schoolNumber="200" individual.staffNumber="110281" individual.personID="738152" individual.gender="F" individual.suffix="" individual.middleName="L" individual.firstName="Janice" individual.lastName="Strothoff">
</person>
        <person 
        individual.alias="" pcontact.email="sandra.stucker@jefferson.kyschools.us" individual.stateID="211009964" schoolEmployment.schoolNumber="200" individual.staffNumber="110510" individual.personID="738269" individual.gender="F" individual.suffix="" individual.middleName="K." individual.firstName="Sandra" individual.lastName="Stucker">
</person>
        <person 
        individual.alias="" pcontact.email="n@n.com" individual.stateID="Incomplete" schoolEmployment.schoolNumber="200" individual.staffNumber="111111" individual.personID="758542" individual.gender="F" individual.suffix="" individual.middleName="" individual.firstName="Teacher" individual.lastName="Substitute">
</person>
        <person 
        individual.alias="" pcontact.email="Julie.Chan@Jefferson.kyschools.us" individual.stateID="211015936" schoolEmployment.schoolNumber="200" individual.staffNumber="109457" individual.personID="525036" individual.gender="F" individual.suffix="" individual.middleName="T" individual.firstName="Julie" individual.lastName="Tallent">
</person>
        <person 
        individual.alias="" pcontact.email="Kris.Tatro@Jefferson.kyschools.us" individual.stateID="211007829" schoolEmployment.schoolNumber="200" individual.staffNumber="107561" individual.personID="736692" individual.gender="F" individual.suffix="" individual.middleName="" individual.firstName="Kris" individual.lastName="Tatro">
</person>
        <person 
        individual.alias="" pcontact.email="Diane.Taylor@Jefferson.kyschools.us" individual.stateID="211005851" schoolEmployment.schoolNumber="200" individual.staffNumber="118553" individual.personID="742585" individual.gender="F" individual.suffix="" individual.middleName="" individual.firstName="Diane" individual.lastName="Taylor">
</person>
        <person 
        individual.alias="" pcontact.email="Glenn.Taylor@Jefferson.kyschools.us" individual.stateID="211001432" schoolEmployment.schoolNumber="200" individual.staffNumber="102636" individual.personID="483737" individual.gender="M" individual.suffix="" individual.middleName="F" individual.firstName="Glenn" individual.lastName="Taylor">
</person>
        <person 
        individual.alias="" pcontact.email="Christy.Teague@jefferson.kyschools.us" individual.stateID="211008729" schoolEmployment.schoolNumber="200" individual.staffNumber="124934" individual.personID="744345" individual.gender="F" individual.suffix="" individual.middleName="D" individual.firstName="Christy" individual.lastName="Teague">
</person>
        <person 
        individual.alias="" pcontact.email="lawrence.thomas@jefferson.kyschools.us" individual.stateID="211016723" schoolEmployment.schoolNumber="200" individual.staffNumber="113991" individual.personID="740127" individual.gender="M" individual.suffix="" individual.middleName="H" individual.firstName="Lawrence" individual.lastName="Thomas">
</person>
        <person 
        individual.alias="" pcontact.email="reginald.thomas@jefferson.kyschools.us" individual.stateID="211008769" schoolEmployment.schoolNumber="200" individual.staffNumber="116535" individual.personID="741485" individual.gender="M" individual.suffix="" individual.middleName="D" individual.firstName="Reginald" individual.lastName="Thomas">
</person>
        <person 
        individual.alias="" pcontact.email="Dawn.Thurman@Jefferson.kyschools.us" individual.stateID="" schoolEmployment.schoolNumber="200" individual.staffNumber="116281" individual.personID="741342" individual.gender="F" individual.suffix="" individual.middleName="" individual.firstName="Dawn" individual.lastName="Thurman">
</person>
        <person 
        individual.alias="" pcontact.email="Mina.Todd@Jefferson.kyschools.us" individual.stateID="211013295" schoolEmployment.schoolNumber="200" individual.staffNumber="114383" individual.personID="740328" individual.gender="F" individual.suffix="" individual.middleName="" individual.firstName="Mina" individual.lastName="Todd">
</person>
        <person 
        individual.alias="" pcontact.email="Clint1.Vaught@jefferson.kyschools.us" individual.stateID="211001635" schoolEmployment.schoolNumber="200" individual.staffNumber="109503" individual.personID="737721" individual.gender="M" individual.suffix="" individual.middleName="" individual.firstName="Clint" individual.lastName="Vaught">
</person>
        <person 
        individual.alias="" pcontact.email="Stacey.Vonroenn@jefferson.kyschools.us" individual.stateID="2120171400" schoolEmployment.schoolNumber="200" individual.staffNumber="111258" individual.personID="758607" individual.gender="F" individual.suffix="" individual.middleName="A" individual.firstName="Stacy" individual.lastName="Vonroenn">
</person>
        <person 
        individual.alias="" pcontact.email="Becky.Wahl@Jefferson.kyschools.us" individual.stateID="211015786" schoolEmployment.schoolNumber="200" individual.staffNumber="121903" individual.personID="743490" individual.gender="F" individual.suffix="" individual.middleName="R" individual.firstName="Becky" individual.lastName="Wahl">
</person>
        <person 
        individual.alias="" pcontact.email="Linda.Wahl@Jefferson.kyschools.us" individual.stateID="211008503" schoolEmployment.schoolNumber="200" individual.staffNumber="105200" individual.personID="735434" individual.gender="F" individual.suffix="" individual.middleName="" individual.firstName="Linda" individual.lastName="Wahl">
</person>
        <person 
        individual.alias="dwalsh1" pcontact.email="Denee.Walsh@Jefferson.kyschools.us" individual.stateID="211010965" schoolEmployment.schoolNumber="200" individual.staffNumber="112837" individual.personID="739487" individual.gender="F" individual.suffix="" individual.middleName="" individual.firstName="Tammy" individual.lastName="Walsh">
</person>
        <person 
        individual.alias="" pcontact.email="Henry.Watson@Jefferson.kyschools.us" individual.stateID="211004180" schoolEmployment.schoolNumber="200" individual.staffNumber="109943" individual.personID="737957" individual.gender="M" individual.suffix="Jr." individual.middleName="F." individual.firstName="Henry" individual.lastName="Watson">
</person>
        <person 
        individual.alias="" pcontact.email="donna.webb@jefferson.kyschools.us" individual.stateID="211013855" schoolEmployment.schoolNumber="200" individual.staffNumber="100397" individual.personID="732838" individual.gender="F" individual.suffix="" individual.middleName="" individual.firstName="Donna" individual.lastName="Webb">
</person>
        <person 
        individual.alias="" pcontact.email="Katherine.weible@jefferson.kyschools.us" individual.stateID="" schoolEmployment.schoolNumber="200" individual.staffNumber="127775" individual.personID="451194" individual.gender="F" individual.suffix="" individual.middleName="B" individual.firstName="Katie" individual.lastName="Weible">
</person>
        <person 
        individual.alias="" pcontact.email="Gary.Weiter@Jefferson.kyschools.us" individual.stateID="211004587" schoolEmployment.schoolNumber="200" individual.staffNumber="101155" individual.personID="733247" individual.gender="M" individual.suffix="" individual.middleName="" individual.firstName="Gary" individual.lastName="Weiter Jr">
</person>
        <person 
        individual.alias="" pcontact.email="Randolf.Wieck@jefferson.kyschools.us" individual.stateID="211014388" schoolEmployment.schoolNumber="200" individual.staffNumber="101597" individual.personID="733489" individual.gender="M" individual.suffix="" individual.middleName="" individual.firstName="Randolph" individual.lastName="Wieck">
</person>
        <person 
        individual.alias="" pcontact.email="Alesia.Williams@Jefferson.kyschools.us" individual.stateID="2120289980" schoolEmployment.schoolNumber="200" individual.staffNumber="116403" individual.personID="741406" individual.gender="F" individual.suffix="" individual.middleName="" individual.firstName="Alesia" individual.lastName="Williams">
</person>
        <person 
        individual.alias="cwillia5" pcontact.email="christopher.williams@jefferson.kyschools.us" individual.stateID="211008941" schoolEmployment.schoolNumber="200" individual.staffNumber="112738" individual.personID="739436" individual.gender="M" individual.suffix="" individual.middleName="A" individual.firstName="Christopher" individual.lastName="Williams">
</person>
        <person 
        individual.alias="" pcontact.email="Scott.Williams@Jefferson.kyschools.us" individual.stateID="211008247" schoolEmployment.schoolNumber="200" individual.staffNumber="120039" individual.personID="742981" individual.gender="M" individual.suffix="" individual.middleName="" individual.firstName="Scott" individual.lastName="Williams">
</person>
        <person 
        individual.alias="" pcontact.email="terry.williams2@jefferson.kyschools.us" individual.stateID="211006976" schoolEmployment.schoolNumber="200" individual.staffNumber="113100" individual.personID="739640" individual.gender="M" individual.suffix="" individual.middleName="A" individual.firstName="Terry" individual.lastName="Williams">
</person>
        <person 
        individual.alias="" pcontact.email="Adam.Wilson@jefferson.kyschools.us" individual.stateID="2120284189" schoolEmployment.schoolNumber="200" individual.staffNumber="127633" individual.personID="829166" individual.gender="M" individual.suffix="" individual.middleName="D" individual.firstName="Adam" individual.lastName="Wilson">
</person>
        <person 
        individual.alias="" pcontact.email="Dana.Wilson@Jefferson.kyschools.us" individual.stateID="211005017" schoolEmployment.schoolNumber="200" individual.staffNumber="109561" individual.personID="724054" individual.gender="F" individual.suffix="" individual.middleName="K" individual.firstName="Dana" individual.lastName="Wilson">
</person>
        <person 
        individual.alias="" pcontact.email="Larry.Wooldridge@Jefferson.kyschools.us" individual.stateID="211011117" schoolEmployment.schoolNumber="200" individual.staffNumber="101833" individual.personID="733620" individual.gender="M" individual.suffix="" individual.middleName="A" individual.firstName="Larry" individual.lastName="Wooldridge">
</person>
        <person 
        individual.alias="" pcontact.email="David.Wright@Jefferson.kyschools.us" individual.stateID="211005686" schoolEmployment.schoolNumber="200" individual.staffNumber="102882" individual.personID="734188" individual.gender="M" individual.suffix="" individual.middleName="M" individual.firstName="David" individual.lastName="Wright">
</person>
        <person 
        individual.alias="" pcontact.email="David.Zuberer@Jefferson.kyschools.us" individual.stateID="211012990" schoolEmployment.schoolNumber="200" individual.staffNumber="101973" individual.personID="733693" individual.gender="M" individual.suffix="" individual.middleName="" individual.firstName="David" individual.lastName="Zuberer">
</person>
        <person 
        individual.alias="" pcontact.email="Glenn.Zwanzig@Jefferson.kyschools.us" individual.stateID="211015244" schoolEmployment.schoolNumber="200" individual.staffNumber="114124" individual.personID="740205" individual.gender="M" individual.suffix="" individual.middleName="" individual.firstName="Glen" individual.lastName="Zwanzig">
</person>
        <person 
        individual.alias="" pcontact.email="Kathy.Zwanzig@Jefferson.kyschools.us" individual.stateID="211008388" schoolEmployment.schoolNumber="200" individual.staffNumber="112953" individual.personID="739558" individual.gender="F" individual.suffix="" individual.middleName="" individual.firstName="Kathy" individual.lastName="Zwanzig">
</person>
      </group>
    </Extract>
  </ExportWizard>
</campusRoot>
